iflow_mcp_revit_mcp-0.5.13.dist-info/licenses/LICENSE
xml_revit_mcp/__init__.py
xml_revit_mcp/prompts.py
xml_revit_mcp/resources.py
xml_revit_mcp/revit_connection.py
xml_revit_mcp/rpc.py
xml_revit_mcp/server.py
xml_revit_mcp/tools.py
iflow_mcp_revit_mcp-0.5.13.dist-info/METADATA
iflow_mcp_revit_mcp-0.5.13.dist-info/WHEEL
iflow_mcp_revit_mcp-0.5.13.dist-info/entry_points.txt
iflow_mcp_revit_mcp-0.5.13.dist-info/top_level.txt
iflow_mcp_revit_mcp-0.5.13.dist-info/RECORD
