Metadata-Version: 2.4
Name: iflow-mcp_revit-mcp
Version: 0.5.13
Summary: revit integration through the Model Context Protocol
Author-email: zedmoster <zedmoster1@gmail.com>
License: MIT
Project-URL: Homepage, https://github.com/zedmoster/revit-mcp
Project-URL: Bug Tracker, https://github.com/zedmoster/revit-mcp/issues
Classifier: Programming Language :: Python :: 3
Classifier: License :: OSI Approved :: MIT License
Classifier: Operating System :: OS Independent
Requires-Python: >=3.10
License-File: LICENSE
Requires-Dist: mcp>=1.3.0
Dynamic: license-file
